{
  "start": [
    45.41146424238291,
    -75.69699773077708
  ],
  "end": [
    45.29735770015956,
    -75.94213808484093
  ],
  "numberOfScenarios": 3,
  "routes": {
    "default": {
      "totalTimeMinutes": 25
    },
    "Safety": {
      "description": "This route prioritizes safer streets with better lighting and lower traffic.",
      "variants": [
        {
          "middle": [
            45.34586898788301,
            -75.74866704443366
          ],
          "tts": [
            4
          ]
        },
        {
          "middle": [
            45.33042787045188,
            -75.76378154531083
          ],
          "tts": [
            6
          ]
        },
        {
          "middle": [
            45.34537358598173,
            -75.66420688040428
          ],
          "tts": [
            10
          ]
        }
      ]
    }
  },
  "survey": [
    {
      "name": "navFrequency",
      "type": "select",
      "options": [
        "Never",
        "Rarely",
        "Sometimes",
        "Often",
        "Always"
      ]
    },
    {
      "name": "age",
      "type": "number"
    },
    {
      "name": "gender",
      "type": "select",
      "options": [
        "Male",
        "Female",
        "Non-binary",
        "Prefer not to say"
      ]
    },
    {
      "name": "primaryTransport",
      "type": "select",
      "options": [
        "Walking",
        "Biking",
        "Public Transit",
        "Car",
        "Other"
      ]
    },
    {
      "name": "comfortNight",
      "type": "range",
      "min": 1,
      "max": 5
    },
    {
      "name": "feedback",
      "type": "text"
    }
  ],
  "consentText": "By completing this survey you agree to take part in a research study about navigation preferences. Participation is voluntary, the survey takes about five minutes, and your responses will remain anonymous. You may skip any question or stop at any time before submitting. By continuing you confirm that you are at least 18 years old and consent to participate."
}
